libChord/__init__.py
libChord/chord.py
libChord/node.py
libChord-1.0.1.dist-info/LICENSE.txt
libChord-1.0.1.dist-info/METADATA
libChord-1.0.1.dist-info/WHEEL
libChord-1.0.1.dist-info/top_level.txt
libChord-1.0.1.dist-info/RECORD
