Metadata-Version: 2.1
Name: libChord
Version: 1.0.1
Summary: This library offers seamless implementation of Chord Protocol. With just as little as two functions you can have a fully functioning decentralized chord network. Read long description to understand how chord protocol works.
Home-page: https://github.com/DheekshithDev/libChord
Author: Dheekshith Mekala (Arth9r)
Author-email: dheekshithdev98@gmail.com
Classifier: Programming Language :: Python :: 3
Classifier: License :: OSI Approved :: MIT License
Classifier: Operating System :: OS Independent
Classifier: Intended Audience :: Developers
Classifier: Development Status :: 4 - Beta
Requires-Python: >=3.6
License-File: LICENSE.txt
Requires-Dist: loguru~=0.7.2
Requires-Dist: cryptography~=43.0.1
